eff_word_net/__init__.py
eff_word_net/audio_processing.py
eff_word_net/audio_utils.py
eff_word_net/create_recordings.py
eff_word_net/engine.py
eff_word_net/generate_reference.py
eff_word_net/single_word_test.py
eff_word_net/streams.py
eff_word_net/models/first_iteration_siamese/baseModel.tflite
eff_word_net/models/first_iteration_siamese/logmelcalc.tflite
eff_word_net/models/resnet_50_arc/slim_93%_accuracy_72.7390%.onnx
eff_word_net/models/resnet_50_arc/slim_93%_accuracy_72.7390%_qint8.onnx
eff_word_net/sample_refs/alexa_ref.json
eff_word_net/sample_refs/balloon_ref.json
eff_word_net/sample_refs/computer_ref.json
eff_word_net/sample_refs/lights_off_ref.json
eff_word_net/sample_refs/lights_on_ref.json
eff_word_net/sample_refs/mobile_ref.json
eff_word_net/sample_refs/mycroft_ref.json
efficientword_net-1.0.5.dist-info/licenses/LICENSE.md
efficientword_net-1.0.5.dist-info/METADATA
efficientword_net-1.0.5.dist-info/WHEEL
efficientword_net-1.0.5.dist-info/top_level.txt
efficientword_net-1.0.5.dist-info/RECORD
