Metadata-Version: 2.4
Name: EfficientWord-Net
Version: 1.0.5
Summary: Few Shot Learning based Hotword Detection Engine
License:                                  Apache License
Project-URL: Homepage, https://github.com/Ant-Brain/EfficientWord
Classifier: Programming Language :: Python :: 3.10
Classifier: Programming Language :: Python :: 3.11
Classifier: Programming Language :: Python :: 3.12
Classifier: Programming Language :: Python :: 3.13
Classifier: Programming Language :: Python :: 3.14
Requires-Python: <3.15,>=3.10
License-File: LICENSE.md
Requires-Dist: numpy
Requires-Dist: onnxruntime
Requires-Dist: pyaudio
Requires-Dist: requests
Requires-Dist: soundfile>=0.13.1
Requires-Dist: twine>=6.2.0
Requires-Dist: typer>=0.21.0
Dynamic: license-file
